{"version":1,"resource":"file:///home/ahmed/dev/codeHub/go/server/notes.rmd","entries":[{"id":"uIW2.rmd","timestamp":1691882564880},{"id":"uXgZ.rmd","timestamp":1691882600688},{"id":"crWS.rmd","timestamp":1691882738600},{"id":"keDR.rmd","timestamp":1691882851752},{"id":"EJmq.rmd","timestamp":1691882893476},{"id":"CXPb.rmd","timestamp":1691883385460},{"id":"NDbT.rmd","timestamp":1691883509080},{"id":"rsIO.rmd","timestamp":1691883522728},{"id":"bEGc.rmd","timestamp":1691883560828},{"id":"p7f2.rmd","timestamp":1691883578496},{"id":"VeFC.rmd","timestamp":1691883616788},{"id":"nT8P.rmd","timestamp":1691883653904},{"id":"7kXR.rmd","timestamp":1691883737608},{"id":"1ZKF.rmd","timestamp":1691883752768},{"id":"Wyk7.rmd","timestamp":1691883884520},{"id":"hhyd.rmd","timestamp":1691883940356},{"id":"3wzD.rmd","timestamp":1691883990804},{"id":"lvYO.rmd","timestamp":1691884009988},{"id":"ChlO.rmd","timestamp":1691884038324},{"id":"Vu3W.rmd","timestamp":1691884052016},{"id":"czom.rmd","timestamp":1691884985016},{"id":"qNDD.rmd","timestamp":1691884997168},{"id":"crx3.rmd","timestamp":1691885029168},{"id":"D0Gu.rmd","timestamp":1691885298472},{"id":"mwSa.rmd","timestamp":1691885350552},{"id":"s4eW.rmd","timestamp":1691885374772},{"id":"PbrY.rmd","timestamp":1691885396776},{"id":"lHFk.rmd","timestamp":1691885433860},{"id":"Ym36.rmd","timestamp":1691885482892},{"id":"nFQ8.rmd","timestamp":1691885607768},{"id":"hoz3.rmd","timestamp":1691885628828},{"id":"dABL.rmd","timestamp":1691885640008},{"id":"I724.rmd","timestamp":1691885783656},{"id":"rYz3.rmd","timestamp":1691885915108},{"id":"Ai6V.rmd","timestamp":1691885939372},{"id":"TWr4.rmd","timestamp":1691886073356}]}