{"version":1,"resource":"file:///home/ahmed/repos/iti-react-tasks/day1/index.html","entries":[{"id":"zPSp.html","timestamp":1691491153305},{"id":"2bte.html","timestamp":1691491269045},{"id":"7sbW.html","timestamp":1691491283445},{"id":"jZbD.html","timestamp":1691491439265},{"id":"HQA7.html","timestamp":1691495250472},{"id":"iGGt.html","timestamp":1691495979512},{"id":"hPAO.html","timestamp":1691495996216},{"id":"gXu4.html","timestamp":1691496010312},{"id":"HNyo.html","timestamp":1691496803984},{"id":"kiuJ.html","timestamp":1691497025672},{"id":"XDG9.html","timestamp":1691497094516},{"id":"zTOS.html","timestamp":1691497111020},{"id":"igTj.html","timestamp":1691497294408},{"id":"kzyT.html","timestamp":1691497744428},{"id":"ODQL.html","timestamp":1691497820396},{"id":"3NdO.html","timestamp":1691497857980},{"id":"u2Z3.html","timestamp":1691497877740},{"id":"uBlm.html","timestamp":1691498192572},{"id":"HAXj.html","timestamp":1691498213048},{"id":"3uOO.html","timestamp":1691498245108}]}